meta_reference/__init__.py
meta_reference/admin.py
meta_reference/apps.py
meta_reference/reference_model_configs.py
meta_reference/tests.py
meta_reference/views.py
meta_reference-0.1.2.dist-info/AUTHORS
meta_reference-0.1.2.dist-info/LICENSE
meta_reference-0.1.2.dist-info/METADATA
meta_reference-0.1.2.dist-info/WHEEL
meta_reference-0.1.2.dist-info/top_level.txt
meta_reference-0.1.2.dist-info/RECORD
