Metadata-Version: 2.1
Name: meta-reference
Version: 0.1.2
Summary: meta
Home-page: https://github.com/meta-trial/meta-reference
Author: Leslie Kepaletswe, Erik van Widenfelt
Author-email: leslie.kep@gmail.com, ew2789@gmail.com
License: GPL license, see LICENSE
Keywords: django edc meta
Platform: UNKNOWN
Classifier: Environment :: Web Environment
Classifier: Framework :: Django
Classifier: Intended Audience :: Developers
Classifier: Intended Audience :: Science/Research
Classifier: License :: OSI Approved :: GNU General Public License v3 (GPLv3)
Classifier: Operating System :: OS Independent
Classifier: Programming Language :: Python :: 3.7
Classifier: Topic :: Internet :: WWW/HTTP
Classifier: Topic :: Internet :: WWW/HTTP :: Dynamic Content
Requires-Dist: edc-reference
